anshika_resume/__init__.py
anshika_resume/main.py
anshika_resume/resume.pdf
anshika_resume-0.0.1.dist-info/METADATA
anshika_resume-0.0.1.dist-info/WHEEL
anshika_resume-0.0.1.dist-info/top_level.txt
anshika_resume-0.0.1.dist-info/RECORD
