Metadata-Version: 2.4
Name: anshika_resume
Version: 0.0.1
Summary: A digital experience for Anshika
Author: Ansh
Classifier: Programming Language :: Python :: 3
Classifier: Operating System :: OS Independent
Requires-Dist: requests
Dynamic: author
Dynamic: classifier
Dynamic: requires-dist
Dynamic: summary
